README.md
setup.py
knocky/__init__.py
knocky/knock.py
knocky.egg-info/PKG-INFO
knocky.egg-info/SOURCES.txt
knocky.egg-info/dependency_links.txt
knocky.egg-info/top_level.txt