Metadata-Version: 2.1
Name: knocky
Version: 1.0
Summary: function callback
Home-page: https://github.com/jdhxyy/knock-python
Author: jdh99
Author-email: jdh821@163.com
License: UNKNOWN
Platform: UNKNOWN
